{
  "data": [
    { "title": 1, "description": "Post 1", "tags": "post 1", "key": "post" },
    { "title": 1, "description": "Post 1", "tags": "post 1", "key": "post" },
    { "title": 1, "description": "Post 1", "tags": "post 1", "key": "post" },
    { "title": 1, "description": "Post 1", "tags": "post 1", "key": "post" },
    { "title": 1, "description": "Post 1", "tags": "post 1", "key": "post" },
    { "title": 1, "description": "Post 1", "tags": "post 1", "key": "post" },
    { "title": 1, "description": "Post 1", "tags": "post 1", "key": "post" },
    { "title": 1, "description": "Post 1", "tags": "post 1", "key": "post" }
  ]
}
